pyme31/__init__.py
pyme31/main.py
pyme31/me31.py
pyme31/measurment.py
pyme31_gamgee-1.0.3.dist-info/LICENSE
pyme31_gamgee-1.0.3.dist-info/METADATA
pyme31_gamgee-1.0.3.dist-info/WHEEL
pyme31_gamgee-1.0.3.dist-info/top_level.txt
pyme31_gamgee-1.0.3.dist-info/RECORD
