Metadata-Version: 2.1
Name: pyme31-gamgee
Version: 1.0.3
Summary: Reads data from Digital Multimeter Metex ME-31 via serial port
Home-page: https://github.com/gamgee/pyme31
Author: Johannes Müller
Author-email: mail@gamgee.de
License: UNKNOWN
Platform: UNKNOWN
Classifier: Programming Language :: Python :: 3
Classifier: License :: OSI Approved :: MIT License
Classifier: Operating System :: OS Independent
Requires-Dist: pyserial
